README.md
setup.py
pycg/__init__.py
pycg/__main__.py
pycg/pycg.py
pycg/formats/__init__.py
pycg/formats/base.py
pycg/formats/fasten.py
pycg/formats/simple.py
pycg/formats/visgraph.py
pycg/machinery/__init__.py
pycg/machinery/callgraph.py
pycg/machinery/classes.py
pycg/machinery/definitions.py
pycg/machinery/imports.py
pycg/machinery/modulecall.py
pycg/machinery/modules.py
pycg/machinery/pointers.py
pycg/machinery/scopes.py
pycg/processing/__init__.py
pycg/processing/base.py
pycg/processing/cgprocessor.py
pycg/processing/postprocessor.py
pycg/processing/preprocessor.py
pycg/utils/__init__.py
pycg/utils/anutils.py
pycg/utils/common.py
pycg/utils/constants.py
xdetection.egg-info/PKG-INFO
xdetection.egg-info/SOURCES.txt
xdetection.egg-info/dependency_links.txt
xdetection.egg-info/entry_points.txt
xdetection.egg-info/requires.txt
xdetection.egg-info/top_level.txt