Metadata-Version: 1.1
Name: xdetection
Version: 0.0.1
Summary: Python Call Relationship Generation Tool BY XARC
Home-page: UNKNOWN
Author: Aloin
Author-email: yinzhou.liu@xtalpi.com
License: UNKNOWN
Platform: UNKNOWN
Classifier: Programming Language :: Python :: 3
